shaped_bloom_filter-3.3.0.1.dist-info/zip-safe
shaped_bloom_filter-3.3.0.1.dist-info/RECORD
shaped_bloom_filter-3.3.0.1.dist-info/top_level.txt
shaped_bloom_filter-3.3.0.1.dist-info/METADATA
shaped_bloom_filter-3.3.0.1.dist-info/LICENSE
shaped_bloom_filter-3.3.0.1.dist-info/WHEEL
tests/test.py
shaped_bloom_filter/filter.py
shaped_bloom_filter/exceptions.py
shaped_bloom_filter/libbloomf.cpython-36m-x86_64-linux-gnu.so
shaped_bloom_filter/libbloomf.cpython-36m-x86_64-linux-gnu.h
shaped_bloom_filter/__init__.py
shaped_bloom_filter/binding.py
shaped_bloom_filter/golib/main.go
shaped_bloom_filter/golib/cdef.h
