Metadata-Version: 2.1
Name: shaped-bloom-filter
Version: 3.3.0.1
Summary: Highly optimized bloom filter in Python with bindings in Go.
Home-page: https://github.com/shaped-ai/bloom
Author: Shaped Team
Author-email: support@shaped.ai
License: UNKNOWN
Keywords: bloom-filter,shaped-ai
Platform: UNKNOWN
Classifier: Operating System :: POSIX :: Linux
Classifier: Operating System :: MacOS :: MacOS X
Classifier: Programming Language :: Python :: 3
Classifier: Development Status :: 5 - Production/Stable
Classifier: Intended Audience :: Developers
License-File: LICENSE
Requires-Dist: cffi (==1.15.1)
